wipeit/__init__.py
wipeit/__main__.py
wipeit/config.yaml
wipeit/app/__init__.py
wipeit/app/client.py
wipeit/commands/__init__.py
wipeit/commands/login.py
wipeit/commands/logout.py
wipeit/commands/wipe.py
wipeit/models/__init__.py
wipeit/models/client.py
wipeit/models/config.py
wipeit/models/history.py
wipeit-0.1.7.dist-info/LICENSE
wipeit-0.1.7.dist-info/METADATA
wipeit-0.1.7.dist-info/WHEEL
wipeit-0.1.7.dist-info/entry_points.txt
wipeit-0.1.7.dist-info/top_level.txt
wipeit-0.1.7.dist-info/RECORD
