Metadata-Version: 2.1
Name: wipeit
Version: 0.1.7
Summary: A small CLI to purge your Reddit history.
Home-page: https://github.com/amickael/wipeit
Author: Andrew Mickael
Author-email: andrew.mickael@gmail.com
License: UNKNOWN
Platform: UNKNOWN
Classifier: Programming Language :: Python :: 3
Classifier: License :: OSI Approved :: MIT License
Classifier: Operating System :: OS Independent
Requires-Python: >=3.7
Requires-Dist: praw (==7.4.0)
Requires-Dist: Click (==8.0.1)
Requires-Dist: pyyaml (==5.4.1)
